os_command_py/__init__.py
os_command_py/os_command.py
os_command_py/test/input/1y0m.pdb
os_command_py/test/input/volume.xvg
os_command_py-1.1.0.dist-info/AUTHORS.rst
os_command_py-1.1.0.dist-info/LICENSE
os_command_py-1.1.0.dist-info/METADATA
os_command_py-1.1.0.dist-info/WHEEL
os_command_py-1.1.0.dist-info/top_level.txt
os_command_py-1.1.0.dist-info/RECORD
