Metadata-Version: 2.1
Name: os-command-py
Version: 1.1.0
Summary: os_command_py is a python library allowing a simplified use of the OS commands.
Home-page: https://github.com/samuelmurail/os_command_py
Author: Samuel Murail
Author-email: samuel.murail@u-paris.fr
License: UNKNOWN
Platform: UNKNOWN
Classifier: Development Status :: 5 - Production/Stable
Classifier: License :: OSI Approved :: GNU General Public License v2 (GPLv2)
Classifier: Natural Language :: English
Classifier: Operating System :: OS Independent
Classifier: Programming Language :: Python :: 3
Classifier: Programming Language :: Python :: 3.8
Classifier: Programming Language :: Python :: 3.7
Classifier: Programming Language :: Python :: 3.6
Classifier: Programming Language :: Python :: 3.5
Classifier: Topic :: Scientific/Engineering :: Bio-Informatics
